gynews3/__init__.py
gynews3/agent/__init__.py
gynews3/agent/__main__.py
gynews3/agent/news_finder/__init__.py
gynews3/agent/news_finder/main.py
gynews3/agent/news_finder/middleware.py
gynews3/agent/news_finder/prompt.py
gynews3/agent/news_reporter/__init__.py
gynews3/agent/news_reporter/main.py
gynews3/agent/news_reporter/prompt.py
gynews3/agent/news_reporter/sub.py
gynews3/agent/news_reporter/tool.py
gynews3/agent/resource_finder/__init__.py
gynews3/agent/resource_finder/main.py
gynews3/agent/resource_finder/middleware.py
gynews3/agent/resource_finder/prompt.py
gynews3/agent/tool.py
gynews3/const.py
gynews3/content.py
gynews3/model.py
gynews3/rag.py
gynews3/spider/__init__.py
gynews3/spider/jp/5ch.py
gynews3/spider/jp/__init__.py
gynews3/spider/jp/asahi.py
gynews3/spider/jp/ats.py
gynews3/spider/jp/chiebukuro.py
gynews3/spider/jp/girlschannel.py
gynews3/spider/jp/hatena.py
gynews3/spider/jp/livedoor.py
gynews3/spider/jp/mainichi.py
gynews3/spider/jp/mbs.py
gynews3/spider/jp/mixi.py
gynews3/spider/jp/note.py
gynews3/spider/jp/rakuten.py
gynews3/spider/jp/shikoku.py
gynews3/spider/jp/tbs.py
gynews3/spider/jp/tsstv.py
gynews3/spider/tec/__init__.py
gynews3/spider/tec/electronicsweekly.py
gynews3/spider/tec/makerpro.py
gynews3/spider/tit/__init__.py
gynews3/spider/tit/arstechnica.py
gynews3/spider/tit/codezine.py
gynews3/spider/tit/infoworld.py
gynews3/spider/tit/zdnet.py
gynews3/spider/tw/__init__.py
gynews3/spider/tw/apple.py
gynews3/spider/tw/cna.py
gynews3/spider/tw/ftvnews.py
gynews3/spider/tw/matters.py
gynews3/spider/tw/pts.py
gynews3/spider/tw/tnn.py
gynews3/spider/util.py
gynews3/summarizer.py
gynews3-0.0.8.dist-info/WHEEL
gynews3-0.0.8.dist-info/METADATA
gynews3-0.0.8.dist-info/RECORD
