Metadata-Version: 2.3
Name: gynews3
Version: 0.0.8
Requires-Dist: deepagents>=0.2.6
Requires-Dist: goose3[all]>=3.1.21
Requires-Dist: huggingface-hub>=1.0.0
Requires-Dist: langchain-text-splitters>=1.0.0
Requires-Dist: numpy>=2.3.4
Requires-Dist: python-dotenv>=1.2.1
Requires-Dist: scrapy>=2.13.3
Requires-Dist: sqlmodel>=0.0.27
Requires-Dist: tavily-python>=0.7.13
Requires-Dist: trafilatura>=2.0.0
Requires-Dist: unstructured>=0.18.21
Requires-Python: >=3.12
